<?xml version="1.0"?>
<EnviarLoteRpsEnvio xmlns="http://www.abrasf.org.br/ABRASF/arquivos/nfse.xsd">
  <LoteRps id="lote1">
    <NumeroLote>1</NumeroLote>
    <Cnpj>78456789000145</Cnpj>
    <InscricaoMunicipal>1</InscricaoMunicipal>
    <QuantidadeRps>1</QuantidadeRps>
    <ListaRps>
      <Rps>
        <InfRps id="rps1">
          <IdentificacaoRps>
            <Nrorps>0</Nrorps>
            <Serie></Serie>
            <Tipo></Tipo>
          </IdentificacaoRps>
          <IdentificacaoNfse>
            <Numero>41</Numero>
            <Serie></Serie>
            <NumeroNFSeSubstituida>0</NumeroNFSeSubstituida>
          </IdentificacaoNfse>
          <DataEmissao>2016-05-31T16:01:12</DataEmissao>
          <Competencia>201605</Competencia>
          <CodigoVerificacao>345123520</CodigoVerificacao>
          <RegimeEspecialTributacao>1</RegimeEspecialTributacao>
          <NaturezaOperacao>1</NaturezaOperacao>
          <OptanteSimplesNacional>1</OptanteSimplesNacional>
          <IncentivadorCultural></IncentivadorCultural>
          <Status>1</Status>
          <Servico>
            <Valores>
              <ValorServicos>855.66</ValorServicos>
              <ValorDeducoes>0.00</ValorDeducoes>
              <ValorPis>1.00</ValorPis>
              <ValorCofins>1.00</ValorCofins>
              <ValorIr>10.00</ValorIr>
              <ValorInss>20.00</ValorInss>
              <ValorCsll>30.00</ValorCsll>
              <IssRetido>1</IssRetido>
              <ValorIss>51.34</ValorIss>
              <ValorIssRetido>51.34</ValorIssRetido>
              <RetencoesFederais>62.00</RetencoesFederais>
              <OutrasRetencoes>0.00</OutrasRetencoes>
              <BaseCalculo>855.66</BaseCalculo>
              <Aliquota>6.00</Aliquota>
              <ValorLiquidoNfse>793.66</ValorLiquidoNfse>
              <DescontoIncondicionado>3.00</DescontoIncondicionado>
              <DescontoCondicionado>2.00</DescontoCondicionado>
            </Valores>
            <ItemListaServico>1103</ItemListaServico>
            <CodigoCnae>8011102</CodigoCnae>
            <AtividadeServico>SERVI&#xC7;OS DE ADESTRAMENTO DE C&#xC3;ES DE GUARDA</AtividadeServico>
            <Discriminacao>565656</Discriminacao>
            <CodigoMunicipio>41609</CodigoMunicipio>
            <CodigoObra></CodigoObra>
            <CodigoArt></CodigoArt>
          </Servico>
          <Prestador>
            <Cnpj>78456789000145</Cnpj>
            <InscricaoMunicipal>1</InscricaoMunicipal>
          </Prestador>
          <Tomador>
            <IdentificacaoTomador>
              <CpfCnpj>
                <CpfTomador>69511179934</CpfTomador>
              </CpfCnpj>
            </IdentificacaoTomador>
            <RazaoSocial>45454</RazaoSocial>
            <Endereco>
              <Endereco>45454</Endereco>
              <Numero>45454</Numero>
              <Bairro>4545</Bairro>
              <CodigoMunicipio>0</CodigoMunicipio>
              <Uf>Paran</Uf>
              <Cep>45454545</Cep>
            </Endereco>
            <Contato>
              <Email>454545</Email>
            </Contato>
          </Tomador>
        </InfRps>
      </Rps>
    </ListaRps>
  </LoteRps>
</EnviarLoteRpsEnvio>
